gcode2dplotterart/Plotter2D.py
gcode2dplotterart/Plotter3D.py
gcode2dplotterart/_Plotter.py
gcode2dplotterart/__init__.py
gcode2dplotterart/experimental_cli.py
gcode2dplotterart/py.typed
gcode2dplotterart/shared_types.py
gcode2dplotterart/experimental_photo_utils/README.md
gcode2dplotterart/experimental_photo_utils/__init__.py
gcode2dplotterart/experimental_photo_utils/load.py
gcode2dplotterart/experimental_photo_utils/process.py
gcode2dplotterart/instruction/InstructionWithArguments.py
gcode2dplotterart/instruction/SimpleInstruction.py
gcode2dplotterart/instruction/__init__.py
gcode2dplotterart/layer/Layer2D.py
gcode2dplotterart/layer/Layer3D.py
gcode2dplotterart/layer/_Layer.py
gcode2dplotterart/layer/__init__.py
gcode2dplotterart/layer/draw_character.py
gcode2dplotterart-2.0.3.dist-info/METADATA
gcode2dplotterart-2.0.3.dist-info/WHEEL
gcode2dplotterart-2.0.3.dist-info/licenses/LICENSE
gcode2dplotterart-2.0.3.dist-info/RECORD
