Metadata-Version: 2.4
Name: gcode2dplotterart
Version: 2.0.3
Summary: A Python library for creating 2D plotter art using GCode
Author: Travis Bumgarner
License-File: LICENSE
Requires-Python: >=3.8
Requires-Dist: matplotlib>=3.8.2
Requires-Dist: numpy>=1.26.4
Requires-Dist: opencv-python>=4.11.0.86
Requires-Dist: pillow>=11.1.0
Requires-Dist: typing-extensions>=4.12.2
